owl_mcp/__init__.py
owl_mcp/axiom_parser.py
owl_mcp/config.py
owl_mcp/format_utils.py
owl_mcp/mcp_tools.py
owl_mcp/owl_api.py
owl_mcp/server.py
owl_mcp/xml_catalog_utils.py
iflow_mcp_scimcp_owl_mcp-0.1.4.dist-info/METADATA
iflow_mcp_scimcp_owl_mcp-0.1.4.dist-info/WHEEL
iflow_mcp_scimcp_owl_mcp-0.1.4.dist-info/entry_points.txt
iflow_mcp_scimcp_owl_mcp-0.1.4.dist-info/RECORD
