Metadata-Version: 2.4
Name: iflow-mcp_scimcp_owl-mcp
Version: 0.1.4
Summary: A MCP server for OWL ontology operations
Author: OWL Server Team
Requires-Python: <=3.13,>=3.10
Requires-Dist: click>=8.0.0
Requires-Dist: mcp>=0.1.0
Requires-Dist: py-horned-owl>=0.1.0
Requires-Dist: pydantic>=2.11.4
Requires-Dist: pyyaml>=6.0.2
Requires-Dist: watchdog>=3.0.0
